Metadata-Version: 2.1
Name: pipreqs-update
Version: 2020.7.1
Summary: update pip requirements file with latest versions
Home-page: https://github.com/andrewp-as-is/pipreqs-update.py
License: Unlicense
Keywords: requirements
Platform: UNKNOWN
Classifier: License :: Public Domain
Classifier: Operating System :: Unix
Classifier: Programming Language :: Python :: 3
Classifier: Programming Language :: Unix Shell
Classifier: Topic :: Utilities
